pass_nice/PASS_NICE.py
pass_nice/__init__.py
pass_nice/exceptions.py
pass_nice/types.py
pass_nice-2.1.1.dist-info/METADATA
pass_nice-2.1.1.dist-info/WHEEL
pass_nice-2.1.1.dist-info/licenses/LICENSE
pass_nice-2.1.1.dist-info/RECORD
