Metadata-Version: 2.4
Name: pass-nice
Version: 2.1.1
Summary: NICE 아이디 본인인증 요청을 자동화해주는 비공식 모듈
Project-URL: Homepage, https://github.com/shy9-29/PASS-NICE
Project-URL: Repository, https://github.com/shy9-29/PASS-NICE
Project-URL: Issues, https://github.com/shy9-29/PASS-NICE/issues
Author-email: Developer <sunr1s2@proton.me>
Maintainer-email: Developer <sunr1s2@proton.me>
License: MIT
License-File: LICENSE
Keywords: authentication,identity,korea,nice,sms,verification
Classifier: Development Status :: 4 - Beta
Classifier: Intended Audience :: Developers
Classifier: License :: OSI Approved :: MIT License
Classifier: Programming Language :: Python :: 3
Classifier: Programming Language :: Python :: 3.9
Classifier: Programming Language :: Python :: 3.10
Classifier: Programming Language :: Python :: 3.11
Classifier: Programming Language :: Python :: 3.12
Classifier: Programming Language :: Python :: 3.13
Classifier: Topic :: Internet :: WWW/HTTP :: Dynamic Content
Classifier: Topic :: Security
Classifier: Topic :: Software Development :: Libraries :: Python Modules
Requires-Python: >=3.9
Requires-Dist: httpx>=0.25.0
